aviary/envs/labbench/__init__.py
aviary/envs/labbench/env.py
aviary/envs/labbench/py.typed
aviary/envs/labbench/task.py
aviary/envs/labbench/version.py
aviary_labbench-0.32.0.dist-info/METADATA
aviary_labbench-0.32.0.dist-info/WHEEL
aviary_labbench-0.32.0.dist-info/top_level.txt
aviary_labbench-0.32.0.dist-info/RECORD
